mypy_8tml
