Metadata-Version: 2.1
Name: mypy8tml
Version: 0.2.1
Summary: A new way to generates html code using class methods in python
Home-page: https://github.com/MikalROn/MyPy8TML
Author: Daniel Coêlho
Author-email: heromon.9010@gmail.com
Maintainer: Daniel Coêlho
Maintainer-email: heromon.9010@gmail.com
License: MIT license
Project-URL: Source, https://github.com/MikalROn/MyPy8TML
Project-URL: Demos, https://github.com/MikalROn/MyPy8TML/tree/main/demos/demo_site
Project-URL: Docs, https://mikalron.github.io/MyPy8TML/
Keywords: html,pyhtml,myhtml,mypyhmtl,8tml,mypyhtml,mypy8tml,
Platform: UNKNOWN
Requires-Python: >=3
License-File: LICENSE
